ltrim/__init__.py
ltrim/__main__.py
ltrim/debloat/__init__.py
ltrim/debloat/__main__.py
ltrim/debloat/debloat.py
ltrim/debloat/process.py
ltrim/debloat/utils.py
ltrim/delta/__init__.py
ltrim/delta/__main__.py
ltrim/delta/delta.py
ltrim/delta/driver.py
ltrim/delta/utils.py
ltrim/moduify/__init__.py
ltrim/moduify/__main__.py
ltrim/moduify/moduifier.py
ltrim/profiler/__init__.py
ltrim/profiler/profiler.py
ltrim/transformers/__init__.py
ltrim/transformers/ast_transformers.py
ltrim/transformers/utils.py
ltrim/utils/__init__.py
ltrim/utils/_io.py
ltrim/utils/config.py
ltrim/utils/constants.py
ltrim/utils/printing.py
ltrim/utils/stats.py
ltrim-0.1.2.dist-info/licenses/LICENSE
ltrim-0.1.2.dist-info/METADATA
ltrim-0.1.2.dist-info/WHEEL
ltrim-0.1.2.dist-info/entry_points.txt
ltrim-0.1.2.dist-info/top_level.txt
ltrim-0.1.2.dist-info/RECORD
