Metadata-Version: 2.4
Name: ltrim
Version: 0.1.2
Summary: Add your description here
Requires-Python: >=3.10
License-File: LICENSE
Requires-Dist: psutil>=6.1.1
Requires-Dist: pycg-fork
Requires-Dist: ruff>=0.9.2
Requires-Dist: setuptools>=75.8.0
Dynamic: license-file
